Metadata-Version: 1.0
Name: tak-distributions
Version: 0.2
Summary: Gaussian & Binomial distributions
Home-page: UNKNOWN
Author: TAK
Author-email: UNKNOWN
License: UNKNOWN
Platform: UNKNOWN
